core/__init__.py
core/connect.py
core/rule_db.py
core/scan.py
HubbleSec-2.0.dist-info/METADATA
HubbleSec-2.0.dist-info/WHEEL
HubbleSec-2.0.dist-info/top_level.txt
HubbleSec-2.0.dist-info/RECORD
